nose_sqlcapture-1.0.7.dist-info/DESCRIPTION.rst
nose_sqlcapture-1.0.7.dist-info/METADATA
nose_sqlcapture-1.0.7.dist-info/RECORD
nose_sqlcapture-1.0.7.dist-info/WHEEL
nose_sqlcapture-1.0.7.dist-info/entry_points.txt
nose_sqlcapture-1.0.7.dist-info/metadata.json
nose_sqlcapture-1.0.7.dist-info/top_level.txt
sqlcapture/__init__.py
sqlcapture/loghandler.py
sqlcapture/plugin.py
