Metadata-Version: 2.0
Name: nose-sqlcapture
Version: 1.0.7
Summary: Capture SQL queries being generated from a nosetests run
Home-page: https://github.com/freshbooks/nose-sqlcapture
Author: Kevin J. Qiu
Author-email: kevin@freshbooks.com
License: BSD
Keywords: nose-sqlcapture
Platform: UNKNOWN
Classifier: Development Status :: 4 - Beta
Classifier: Intended Audience :: Developers
Classifier: License :: OSI Approved :: BSD License
Classifier: Natural Language :: English
Classifier: Programming Language :: Python :: 2
Classifier: Programming Language :: Python :: 2.6
Classifier: Programming Language :: Python :: 2.7
Requires-Dist: sqlparse (==0.2.4)
Requires-Dist: future
